dfreproject/__init__.py
dfreproject/reproject.py
dfreproject/sip.py
dfreproject/tensorhdu.py
dfreproject/utils.py
dfreproject-1.2.0.dist-info/licenses/LICENSE
dfreproject-1.2.0.dist-info/METADATA
dfreproject-1.2.0.dist-info/WHEEL
dfreproject-1.2.0.dist-info/top_level.txt
dfreproject-1.2.0.dist-info/RECORD
