Metadata-Version: 2.4
Name: dfreproject
Version: 1.2.0
Summary: A high-performance Python package for reprojecting astronomical images between different coordinate systems with support for SIP distortion correction.
Author-email: Carter Rhea <carter.rhea@dragonfly1000.com>
Project-URL: Homepage, https://github.com/DragonflyTelescope/dfreproject
Project-URL: Issues, https://github.com/DragonflyTelescope/dfreproject/issues
Classifier: Development Status :: 3 - Alpha
Classifier: Intended Audience :: Science/Research
Classifier: Topic :: Scientific/Engineering :: Astronomy
Classifier: Programming Language :: Python :: 3
Classifier: Programming Language :: Python :: 3.8
Classifier: Operating System :: OS Independent
Requires-Python: >=3.8
License-File: LICENSE
Requires-Dist: numpy>=1.17.0
Requires-Dist: astropy>=4.0
Requires-Dist: torch>=1.9.0
Provides-Extra: docs
Requires-Dist: sphinx>=5.0.0; extra == "docs"
Requires-Dist: sphinx-rtd-theme>=1.0.0; extra == "docs"
Requires-Dist: sphinx-autoapi>=2.0.0; extra == "docs"
Requires-Dist: nbsphinx>=0.8.9; extra == "docs"
Requires-Dist: ipykernel>=6.0.0; extra == "docs"
Requires-Dist: matplotlib>=3.4.0; extra == "docs"
Requires-Dist: sphinx-copybutton==0.5.2; extra == "docs"
Dynamic: license-file
